easyTypeWriter/__init__.py
easyTypeWriter/typeWriter.py
easyTypeWriter-0.23.dist-info/LICENSE
easyTypeWriter-0.23.dist-info/METADATA
easyTypeWriter-0.23.dist-info/WHEEL
easyTypeWriter-0.23.dist-info/top_level.txt
easyTypeWriter-0.23.dist-info/RECORD
