Metadata-Version: 2.1
Name: easyTypeWriter
Version: 0.23
Summary: This module lets you quickly add type writer sound effect for inputs to your python project
Home-page: https://github.com/harshnative/easyTypeWriter_module_python
Author: Harsh Native
Author-email: Harshnative@gmail.com
License: UNKNOWN
Platform: UNKNOWN
Classifier: Programming Language :: Python :: 3
Classifier: License :: OSI Approved :: MIT License
Classifier: Operating System :: OS Independent
Requires-Python: >=3.6
Requires-Dist: playsound
